pycopancore/__init__.py
pycopancore/_version.py
pycopancore/data_model/__init__.py
pycopancore/data_model/dimension.py
pycopancore/data_model/dimensional_quantity.py
pycopancore/data_model/ordered_set.py
pycopancore/data_model/reference_variable.py
pycopancore/data_model/set_variable.py
pycopancore/data_model/unit.py
pycopancore/data_model/variable.py
pycopancore/data_model/master_data_model/__init__.py
pycopancore/data_model/master_data_model/cell.py
pycopancore/data_model/master_data_model/culture.py
pycopancore/data_model/master_data_model/dimensions_and_units.py
pycopancore/data_model/master_data_model/environment.py
pycopancore/data_model/master_data_model/group.py
pycopancore/data_model/master_data_model/individual.py
pycopancore/data_model/master_data_model/metabolism.py
pycopancore/data_model/master_data_model/social_system.py
pycopancore/data_model/master_data_model/world.py
pycopancore/model_components/__init__.py
pycopancore/model_components/abstract/__init__.py
pycopancore/model_components/abstract/cell.py
pycopancore/model_components/abstract/culture.py
pycopancore/model_components/abstract/environment.py
pycopancore/model_components/abstract/group.py
pycopancore/model_components/abstract/individual.py
pycopancore/model_components/abstract/metabolism.py
pycopancore/model_components/abstract/model.py
pycopancore/model_components/abstract/social_system.py
pycopancore/model_components/abstract/world.py
pycopancore/model_components/base/__init__.py
pycopancore/model_components/base/interface.py
pycopancore/model_components/base/model.py
pycopancore/model_components/base/model_logics.py
pycopancore/model_components/base/implementation/__init__.py
pycopancore/model_components/base/implementation/cell.py
pycopancore/model_components/base/implementation/culture.py
pycopancore/model_components/base/implementation/environment.py
pycopancore/model_components/base/implementation/group.py
pycopancore/model_components/base/implementation/individual.py
pycopancore-0.9.0.dist-info/METADATA
pycopancore-0.9.0.dist-info/WHEEL
pycopancore-0.9.0.dist-info/licenses/LICENSE
pycopancore-0.9.0.dist-info/RECORD
