Metadata-Version: 2.4
Name: pycopancore
Version: 0.9.0
Summary: Reference implementation of the copan:CORE World-Earth modelling framework
Project-URL: Homepage, https://github.com/pik-copan/pycopancore
Project-URL: Issues, https://github.com/pik-copan/pycopancore/issues
Project-URL: Repository, https://github.com/pik-copan/pycopancore
Author-email: "COPAN team @ PIK" <core@pik-potsdam.de>
License: BSD 2-Clause License
License-File: LICENSE
Keywords: ABM,DGVM,World-Earth,framework,modelling
Classifier: Development Status :: 4 - Beta
Classifier: Intended Audience :: Developers
Classifier: Intended Audience :: Science/Research
Classifier: Operating System :: OS Independent
Classifier: Programming Language :: Python
Classifier: Programming Language :: Python :: 3.9
Classifier: Programming Language :: Python :: 3.10
Classifier: Programming Language :: Python :: 3.11
Classifier: Programming Language :: Python :: 3.12
Classifier: Topic :: Scientific/Engineering
Classifier: Topic :: Software Development :: Libraries
Requires-Python: >=3.9
Requires-Dist: numba
Requires-Dist: numpy>=1.11.0
Requires-Dist: profilehooks
Requires-Dist: pycoupler>=1.5.16
Requires-Dist: python-louvain>=0.9
Requires-Dist: scipy>=0.17.0
Requires-Dist: sympy>=1.0
Provides-Extra: dev
Requires-Dist: black; extra == 'dev'
Requires-Dist: flake8; extra == 'dev'
Requires-Dist: pytest; extra == 'dev'
Requires-Dist: pytest-cov; extra == 'dev'
